mermake/__init__.py
mermake/__main__.py
mermake/align.py
mermake/block.py
mermake/blur.cu
mermake/blur.py
mermake/decoder.py
mermake/deconvolver.py
mermake/fill.py
mermake/io.py
mermake/ioMicro.py
mermake/math.py
mermake/maxima.cu
mermake/maxima.py
mermake/utils.py
mermake-0.0.73.dist-info/licenses/LICENSE
other/__init__.py
other/filters.py
other/io.py
other/maxima.py
other/more.py
mermake-0.0.73.dist-info/METADATA
mermake-0.0.73.dist-info/WHEEL
mermake-0.0.73.dist-info/entry_points.txt
mermake-0.0.73.dist-info/top_level.txt
mermake-0.0.73.dist-info/RECORD
