Metadata-Version: 2.4
Name: mermake
Version: 0.0.73
Summary: Code to process merfish data
Home-page: https://github.com/deprekate/mermake
Author: Katelyn McNair
Author-email: deprekate@gmail.com
Classifier: Programming Language :: Python :: 3
Classifier: License :: OSI Approved :: GNU General Public License v3 or later (GPLv3+)
Classifier: Operating System :: OS Independent
Requires-Python: >3.5.2
License-File: LICENSE
Requires-Dist: dask
Requires-Dist: zarr
Requires-Dist: numpy
Requires-Dist: cupy-cuda12x
Dynamic: author
Dynamic: author-email
Dynamic: classifier
Dynamic: description
Dynamic: description-content-type
Dynamic: home-page
Dynamic: license-file
Dynamic: requires-dist
Dynamic: requires-python
Dynamic: summary
